LICENSE
MANIFEST.in
README
bootstrap.py
buildout.cfg
setup.py
src/pythogram/__init__.py
src/pythogram/development.py
src/pythogram/models.py
src/pythogram/urls.py
src/pythogram/views.py
src/pythogram.egg-info/PKG-INFO
src/pythogram.egg-info/SOURCES.txt
src/pythogram.egg-info/dependency_links.txt
src/pythogram.egg-info/entry_points.txt
src/pythogram.egg-info/not-zip-safe
src/pythogram.egg-info/top_level.txt