Metadata-Version: 1.0
Name: pythogram
Version: 0.0
Summary: A django app for distributed photogrammetric computations
Home-page: http://github.com/cpsaltis/pythogram
Author: Christodoulos Psaltis
Author-email: cpsaltis@unweb.me
License: BSD License
Platform: UNKNOWN
